synapse_selector/__init__.py
synapse_selector/__main__.py
synapse_selector/assets/add.svg
synapse_selector/assets/back.svg
synapse_selector/assets/home.svg
synapse_selector/assets/keep.svg
synapse_selector/assets/open.svg
synapse_selector/assets/peak.svg
synapse_selector/assets/save.svg
synapse_selector/assets/settings.svg
synapse_selector/assets/trash.svg
synapse_selector/detection/__init__.py
synapse_selector/detection/model_wraper.py
synapse_selector/detection/model_zoo.py
synapse_selector/detection/peak_detection.py
synapse_selector/gui/__init__.py
synapse_selector/gui/add_window.py
synapse_selector/gui/gui.py
synapse_selector/gui/settingswindow.py
synapse_selector/settings/default_settings.json
synapse_selector/utils/__init__.py
synapse_selector/utils/configuration.py
synapse_selector/utils/export.py
synapse_selector/utils/hash.py
synapse_selector/utils/normalization.py
synapse_selector/utils/plot.py
synapse_selector/utils/post_selection/__init__.py
synapse_selector/utils/post_selection/decay_compute.py
synapse_selector/utils/post_selection/failure_rate.py
synapse_selector/utils/threshold.py
synapse_selector/utils/trace_data.py
synapse_selector-0.2.13.dist-info/LICENSE
synapse_selector-0.2.13.dist-info/METADATA
synapse_selector-0.2.13.dist-info/WHEEL
synapse_selector-0.2.13.dist-info/entry_points.txt
synapse_selector-0.2.13.dist-info/RECORD
