Metadata-Version: 2.1
Name: synapse-selector
Version: 0.2.13
Summary: Small internal package for post-selection of Glutmate/Calcium signal responses.
Author: Stephan Weissbach
Author-email: s.weissbach@uni-mainz.de
Requires-Python: >=3.9,<3.13
Classifier: Programming Language :: Python :: 3
Classifier: Programming Language :: Python :: 3.9
Classifier: Programming Language :: Python :: 3.10
Classifier: Programming Language :: Python :: 3.11
Requires-Dist: numpy (>=1.26.1,<2.0.0)
Requires-Dist: openpyxl (>=3.1.2,<4.0.0)
Requires-Dist: pandas (>=2.1.1,<3.0.0)
Requires-Dist: plotly (>=5.17.0,<6.0.0)
Requires-Dist: pyqt6-webengine (>=6.6.0,<7.0.0)
Requires-Dist: requests (>=2.31.0,<3.0.0)
Requires-Dist: scipy (>=1.11.3,<2.0.0)
Requires-Dist: torch (>=2.1.1,<3.0.0)
